{"type":"PR","pr":{"number":64,"head":"baab247f72ea538af68fc6c051f2eaf165c4d62f"},"user":"Radio Arcane","status":"draft","branch":"cms/arcane-alive-2019-10-11","collection":"events","title":"2019-10-11 Arcane Alive","description":"Arcane Alive! Featuring live performances by:\n\n\n\n\n**WINGTIPS** : electronic, dream pop, electronica, gothpop, post-punk, synthpop from Chicago  \nhttps://wingtips.bandcamp.com  \n\n\n\n**SCARY BLACK** : alternative, darkwave, goth, nightmare pop, post-punk  from Louisville  \nhttps://scaryblack.bandcamp.com\n\n\n\n**Vyva Melinkolya** : alternative, dream-pop, ethereal goth, nugaze psychedelic-pop, shoegaze, transgender from Louisville  \nhttps://vyva-melinkolyaky.bandcamp.com\n\n\n\nAlso added to the night :\n\n\n\n**Hypnagogue** :  ambient, drone electroacoustic, experimental, minimalism from Massachusetts  \nhttps://hypnagogue.bandcamp.com  \n\n\n\nRadio Arcane djs between sets and after performance.\n\n\n\n18+ to enter   \n21+ bar  \n$10 admission\n\n\n\n\nThis is a Friday night so, we're gonna make this a party! Come early, stay late! Doors at 9pm\n\n\n\n\n *Lineup order will most likely be :  \n Hypnagogue  \n Vyva Melinkolya  \n Wingtips   \n Scary Black  \n *possible changes in order","objects":{"entry":{"path":"_posts/events/arcane-alive-2019-10-11.md","sha":"f90f68ee8b63aae41c6ee7a925627f17fd190a28"},"files":[]},"timeStamp":"2019-09-12T20:37:20.355Z"}